django_floc_disable/__init__.py
django_floc_disable/_version.py
django_floc_disable/apps.py
django_floc_disable/middleware.py
tests/__init__.py
tests/test_settings.py
tests/test_urls.py
tests/tests.py
django_floc_disable-1.2.0.dist-info/LICENSE.txt
django_floc_disable-1.2.0.dist-info/METADATA
django_floc_disable-1.2.0.dist-info/WHEEL
django_floc_disable-1.2.0.dist-info/top_level.txt
django_floc_disable-1.2.0.dist-info/RECORD
