Metadata-Version: 2.1
Name: django-floc-disable
Version: 1.2.0
Summary: Django middleware to disable Google FLoC tracking
Home-page: https://github.com/nhymxu/django-floc-disable
Author: Dung Nguyen
Project-URL: Bug Tracker, https://github.com/nhymxu/django-floc-disable/issues
Project-URL: Funding, https://dungnt.net/donate.html
Classifier: License :: OSI Approved :: MIT License
Classifier: Operating System :: OS Independent
Classifier: Programming Language :: Python :: 3
Classifier: Programming Language :: Python :: 3.8
Classifier: Programming Language :: Python :: 3.9
Classifier: Programming Language :: Python :: 3.10
Classifier: Programming Language :: Python :: 3.11
Classifier: Programming Language :: Python :: 3.12
Classifier: Programming Language :: Python :: 3.13
Classifier: Programming Language :: Python :: 3 :: Only
Requires-Python: >=3.8
License-File: LICENSE.txt
Requires-Dist: Django
